measurement/__init__.py
measurement/_version.py
measurement/base.py
measurement/utils.py
measurement/measures/__init__.py
measurement/measures/capacitance.py
measurement/measures/current.py
measurement/measures/distance.py
measurement/measures/energy.py
measurement/measures/frequency.py
measurement/measures/mass.py
measurement/measures/pressure.py
measurement/measures/radioactivity.py
measurement/measures/resistance.py
measurement/measures/speed.py
measurement/measures/temperature.py
measurement/measures/time.py
measurement/measures/voltage.py
measurement/measures/volume.py
measurement/measures/volumetric_flow.py
measurement-3.2.1.dist-info/LICENSE
measurement-3.2.1.dist-info/WHEEL
measurement-3.2.1.dist-info/METADATA
measurement-3.2.1.dist-info/RECORD
